{
  "strategyName": "Basic v1.2",
  "strategy": [
    {
      "startPhase": "start",
      "endPhase": "challenge10",
      "corruptions": {
        "viscosity": 0,
        "drought": 0,
        "deflation": 0,
        "extinction": 0,
        "illiteracy": 0,
        "recession": 0,
        "dilation": 0,
        "hyperchallenge": 0
      },
      "corruptionLoadoutName": null,
      "strat": [
        {
          "challengeNumber": 305,
          "challengeCompletions": 0,
          "challengeWaitTime": 0,
          "challengeWaitBefore": 0,
          "challengeMaxTime": 0
        },
        {
          "challengeNumber": 152,
          "challengeCompletions": 0,
          "challengeWaitTime": 0,
          "challengeWaitBefore": 10,
          "challengeMaxTime": 0
        },
        {
          "challengeNumber": 1,
          "challengeCompletions": 0,
          "challengeWaitTime": 0,
          "challengeWaitBefore": 0,
          "challengeMaxTime": 10000
        },
        {
          "challengeNumber": 2,
          "challengeCompletions": 0,
          "challengeWaitTime": 0,
          "challengeWaitBefore": 10,
          "challengeMaxTime": 1000000
        },
        {
          "challengeNumber": 3,
          "challengeCompletions": 0,
          "challengeWaitTime": 0,
          "challengeWaitBefore": 10,
          "challengeMaxTime": 1000000
        },
        {
          "challengeNumber": 4,
          "challengeCompletions": 0,
          "challengeWaitTime": 0,
          "challengeWaitBefore": 10,
          "challengeMaxTime": 1000000
        },
        {
          "challengeNumber": 5,
          "challengeCompletions": 0,
          "challengeWaitTime": 0,
          "challengeWaitBefore": 10,
          "challengeMaxTime": 1000000
        },
        {
          "challengeNumber": 6,
          "challengeCompletions": 0,
          "challengeWaitTime": 0,
          "challengeWaitBefore": 10,
          "challengeMaxTime": 1000000
        },
        {
          "challengeNumber": 7,
          "challengeCompletions": 0,
          "challengeWaitTime": 0,
          "challengeWaitBefore": 10,
          "challengeMaxTime": 1000000
        },
        {
          "challengeNumber": 8,
          "challengeCompletions": 0,
          "challengeWaitTime": 0,
          "challengeWaitBefore": 10,
          "challengeMaxTime": 1000000
        },
        {
          "challengeNumber": 9,
          "challengeCompletions": 0,
          "challengeWaitTime": 0,
          "challengeWaitBefore": 10,
          "challengeMaxTime": 1000000
        },
        {
          "challengeNumber": 102,
          "challengeCompletions": 0,
          "challengeWaitTime": 0,
          "challengeWaitBefore": 10,
          "challengeMaxTime": 0
        },
        {
          "challengeNumber": 10,
          "challengeCompletions": 1,
          "challengeWaitTime": 0,
          "challengeWaitBefore": 250,
          "challengeMaxTime": 1000000
        },
        {
          "challengeNumber": 102,
          "challengeCompletions": 0,
          "challengeWaitTime": 0,
          "challengeWaitBefore": 10,
          "challengeMaxTime": 0
        },
        {
          "challengeNumber": 301,
          "challengeCompletions": 0,
          "challengeWaitTime": 0,
          "challengeWaitBefore": 0,
          "challengeMaxTime": 0
        },
        {
          "challengeNumber": 104,
          "challengeCompletions": 0,
          "challengeWaitTime": 0,
          "challengeWaitBefore": 0,
          "challengeMaxTime": 0
        }
      ]
    },
    {
      "startPhase": "challenge10",
      "endPhase": "singularity",
      "corruptions": {
        "viscosity": 0,
        "drought": 0,
        "deflation": 0,
        "extinction": 0,
        "illiteracy": 0,
        "recession": 0,
        "dilation": 0,
        "hyperchallenge": 0
      },
      "corruptionLoadoutName": null,
      "strat": [
        {
          "challengeNumber": 11,
          "challengeCompletions": 0,
          "challengeWaitTime": 0,
          "challengeWaitBefore": 0,
          "challengeMaxTime": 10000
        },
        {
          "challengeNumber": 10,
          "challengeCompletions": 1,
          "challengeWaitTime": 0,
          "challengeWaitBefore": 0,
          "challengeMaxTime": 1000000
        },
        {
          "challengeNumber": 102,
          "challengeCompletions": 0,
          "challengeWaitTime": 0,
          "challengeWaitBefore": 100,
          "challengeMaxTime": 0
        },
        {
          "challengeNumber": 12,
          "challengeCompletions": 0,
          "challengeWaitTime": 0,
          "challengeWaitBefore": 0,
          "challengeMaxTime": 1000000
        },
        {
          "challengeNumber": 10,
          "challengeCompletions": 1,
          "challengeWaitTime": 0,
          "challengeWaitBefore": 0,
          "challengeMaxTime": 1000000
        },
        {
          "challengeNumber": 102,
          "challengeCompletions": 0,
          "challengeWaitTime": 0,
          "challengeWaitBefore": 100,
          "challengeMaxTime": 0
        },
        {
          "challengeNumber": 13,
          "challengeCompletions": 0,
          "challengeWaitTime": 0,
          "challengeWaitBefore": 0,
          "challengeMaxTime": 1000000
        },
        {
          "challengeNumber": 10,
          "challengeCompletions": 1,
          "challengeWaitTime": 0,
          "challengeWaitBefore": 0,
          "challengeMaxTime": 1000000
        },
        {
          "challengeNumber": 102,
          "challengeCompletions": 0,
          "challengeWaitTime": 0,
          "challengeWaitBefore": 100,
          "challengeMaxTime": 0
        },
        {
          "challengeNumber": 14,
          "challengeCompletions": 0,
          "challengeWaitTime": 0,
          "challengeWaitBefore": 0,
          "challengeMaxTime": 1000000
        },
        {
          "challengeNumber": 10,
          "challengeCompletions": 1,
          "challengeWaitTime": 0,
          "challengeWaitBefore": 0,
          "challengeMaxTime": 1000000
        },
        {
          "challengeNumber": 102,
          "challengeCompletions": 0,
          "challengeWaitTime": 0,
          "challengeWaitBefore": 100,
          "challengeMaxTime": 0
        },
        {
          "challengeNumber": 15,
          "challengeCompletions": 0,
          "challengeWaitTime": 0,
          "challengeWaitBefore": 0,
          "challengeMaxTime": 10000
        },
        {
          "challengeNumber": 1,
          "challengeCompletions": 0,
          "challengeWaitTime": 0,
          "challengeWaitBefore": 0,
          "challengeMaxTime": 1000000
        },
        {
          "challengeNumber": 2,
          "challengeCompletions": 0,
          "challengeWaitTime": 0,
          "challengeWaitBefore": 10,
          "challengeMaxTime": 1000000
        },
        {
          "challengeNumber": 3,
          "challengeCompletions": 0,
          "challengeWaitTime": 0,
          "challengeWaitBefore": 10,
          "challengeMaxTime": 1000000
        },
        {
          "challengeNumber": 4,
          "challengeCompletions": 0,
          "challengeWaitTime": 0,
          "challengeWaitBefore": 10,
          "challengeMaxTime": 1000000
        },
        {
          "challengeNumber": 5,
          "challengeCompletions": 0,
          "challengeWaitTime": 0,
          "challengeWaitBefore": 10,
          "challengeMaxTime": 1000000
        },
        {
          "challengeNumber": 6,
          "challengeCompletions": 0,
          "challengeWaitTime": 0,
          "challengeWaitBefore": 10,
          "challengeMaxTime": 1000000
        },
        {
          "challengeNumber": 7,
          "challengeCompletions": 0,
          "challengeWaitTime": 0,
          "challengeWaitBefore": 10,
          "challengeMaxTime": 1000000
        },
        {
          "challengeNumber": 102,
          "challengeCompletions": 0,
          "challengeWaitTime": 0,
          "challengeWaitBefore": 10,
          "challengeMaxTime": 0
        },
        {
          "challengeNumber": 202,
          "challengeCompletions": 0,
          "challengeWaitTime": 0,
          "challengeWaitBefore": 0,
          "challengeMaxTime": 0,
          "loadoutName": "Post-C15"
        },
        {
          "challengeNumber": 103,
          "challengeCompletions": 0,
          "challengeWaitTime": 0,
          "challengeWaitBefore": 100,
          "challengeMaxTime": 0
        },
        {
          "challengeNumber": 10,
          "challengeCompletions": 1,
          "challengeWaitTime": 0,
          "challengeWaitBefore": 0,
          "challengeMaxTime": 1000000
        },
        {
          "challengeNumber": 400,
          "challengeCompletions": 0,
          "challengeWaitTime": 0,
          "challengeWaitBefore": 100,
          "challengeMaxTime": 0
        }
      ]
    },
    {
      "startPhase": "singularity",
      "endPhase": "end",
      "corruptions": {
        "viscosity": 0,
        "drought": 0,
        "deflation": 0,
        "extinction": 0,
        "illiteracy": 0,
        "recession": 0,
        "dilation": 0,
        "hyperchallenge": 0
      },
      "corruptionLoadoutName": null,
      "strat": [
        {
          "challengeNumber": 302,
          "challengeCompletions": 0,
          "challengeWaitTime": 0,
          "challengeWaitBefore": 0,
          "challengeMaxTime": 0
        },
        {
          "challengeNumber": 10,
          "challengeCompletions": 1,
          "challengeWaitTime": 0,
          "challengeWaitBefore": 100,
          "challengeMaxTime": 10000
        },
        {
          "challengeNumber": 104,
          "challengeCompletions": 0,
          "challengeWaitTime": 0,
          "challengeWaitBefore": 100,
          "challengeMaxTime": 1000000
        },
        {
          "challengeNumber": 212,
          "challengeCompletions": 1,
          "challengeWaitTime": 0,
          "challengeWaitBefore": 0,
          "challengeMaxTime": 10000
        },
        {
          "challengeNumber": 214,
          "challengeCompletions": 0,
          "challengeWaitTime": 0,
          "challengeWaitBefore": 10,
          "challengeMaxTime": 10000
        },
        {
          "challengeNumber": 15,
          "challengeCompletions": 0,
          "challengeWaitTime": 0,
          "challengeWaitBefore": 10,
          "challengeMaxTime": 10000
        },
        {
          "challengeNumber": 610,
          "challengeCompletions": 0,
          "challengeWaitTime": 0,
          "challengeWaitBefore": 50,
          "challengeMaxTime": 0
        },
        {
          "challengeNumber": 102,
          "challengeCompletions": 0,
          "challengeWaitTime": 0,
          "challengeWaitBefore": 0,
          "challengeMaxTime": 0
        },
        {
          "challengeNumber": 152,
          "challengeCompletions": 0,
          "challengeWaitTime": 0,
          "challengeWaitBefore": 0,
          "challengeMaxTime": 0
        },
        {
          "challengeNumber": 8,
          "challengeCompletions": 0,
          "challengeWaitTime": 0,
          "challengeWaitBefore": 0,
          "challengeMaxTime": 1000000
        },
        {
          "challengeNumber": 104,
          "challengeCompletions": 0,
          "challengeWaitTime": 0,
          "challengeWaitBefore": 100,
          "challengeMaxTime": 0
        },
        {
          "challengeNumber": 152,
          "challengeCompletions": 0,
          "challengeWaitTime": 0,
          "challengeWaitBefore": 10,
          "challengeMaxTime": 0
        },
        {
          "challengeNumber": 602,
          "challengeCompletions": 0,
          "challengeWaitTime": 0,
          "challengeWaitBefore": 10,
          "challengeMaxTime": 0
        },
        {
          "challengeNumber": 607,
          "challengeCompletions": 0,
          "challengeWaitTime": 0,
          "challengeWaitBefore": 10,
          "challengeMaxTime": 0
        },
        {
          "challengeNumber": 610,
          "challengeCompletions": 0,
          "challengeWaitTime": 0,
          "challengeWaitBefore": 10,
          "challengeMaxTime": 0
        },
        {
          "challengeNumber": 8,
          "challengeCompletions": 0,
          "challengeWaitTime": 0,
          "challengeWaitBefore": 0,
          "challengeMaxTime": 1000000
        },
        {
          "challengeNumber": 202,
          "challengeCompletions": 0,
          "challengeWaitTime": 0,
          "challengeWaitBefore": 0,
          "challengeMaxTime": 0,
          "loadoutName": "Full"
        },
        {
          "challengeNumber": 103,
          "challengeCompletions": 0,
          "challengeWaitTime": 0,
          "challengeWaitBefore": 50,
          "challengeMaxTime": 0
        },
        {
          "challengeNumber": 152,
          "challengeCompletions": 0,
          "challengeWaitTime": 0,
          "challengeWaitBefore": 10,
          "challengeMaxTime": 0
        },
        {
          "challengeNumber": 602,
          "challengeCompletions": 0,
          "challengeWaitTime": 0,
          "challengeWaitBefore": 50,
          "challengeMaxTime": 0
        },
        {
          "challengeNumber": 607,
          "challengeCompletions": 0,
          "challengeWaitTime": 0,
          "challengeWaitBefore": 50,
          "challengeMaxTime": 0
        },
        {
          "challengeNumber": 610,
          "challengeCompletions": 0,
          "challengeWaitTime": 0,
          "challengeWaitBefore": 120,
          "challengeMaxTime": 0
        },
        {
          "challengeNumber": 15,
          "challengeCompletions": 0,
          "challengeWaitTime": 0,
          "challengeWaitBefore": 0,
          "challengeMaxTime": 1000000
        },
        {
          "challengeNumber": 152,
          "challengeCompletions": 0,
          "challengeWaitTime": 0,
          "challengeWaitBefore": 10,
          "challengeMaxTime": 0
        },
        {
          "challengeNumber": 1,
          "challengeCompletions": 0,
          "challengeWaitTime": 0,
          "challengeWaitBefore": 0,
          "challengeMaxTime": 1000000
        },
        {
          "challengeNumber": 2,
          "challengeCompletions": 0,
          "challengeWaitTime": 0,
          "challengeWaitBefore": 10,
          "challengeMaxTime": 1000000
        },
        {
          "challengeNumber": 3,
          "challengeCompletions": 0,
          "challengeWaitTime": 0,
          "challengeWaitBefore": 10,
          "challengeMaxTime": 1000000
        },
        {
          "challengeNumber": 4,
          "challengeCompletions": 0,
          "challengeWaitTime": 0,
          "challengeWaitBefore": 10,
          "challengeMaxTime": 1000000
        },
        {
          "challengeNumber": 5,
          "challengeCompletions": 0,
          "challengeWaitTime": 10,
          "challengeWaitBefore": 10,
          "challengeMaxTime": 1000000
        },
        {
          "challengeNumber": 6,
          "challengeCompletions": 0,
          "challengeWaitTime": 10,
          "challengeWaitBefore": 10,
          "challengeMaxTime": 1000000
        },
        {
          "challengeNumber": 7,
          "challengeCompletions": 0,
          "challengeWaitTime": 10,
          "challengeWaitBefore": 10,
          "challengeMaxTime": 1000000
        },
        {
          "challengeNumber": 9,
          "challengeCompletions": 0,
          "challengeWaitTime": 10,
          "challengeWaitBefore": 10,
          "challengeMaxTime": 1000000
        },
        {
          "challengeNumber": 10,
          "challengeCompletions": 0,
          "challengeWaitTime": 10,
          "challengeWaitBefore": 10,
          "challengeMaxTime": 1000000
        },
        {
          "challengeNumber": 8,
          "challengeCompletions": 0,
          "challengeWaitTime": 10,
          "challengeWaitBefore": 10,
          "challengeMaxTime": 1000000
        },
        {
          "challengeNumber": 152,
          "challengeCompletions": 0,
          "challengeWaitTime": 0,
          "challengeWaitBefore": 10,
          "challengeMaxTime": 0
        },
        {
          "challengeNumber": 103,
          "challengeCompletions": 0,
          "challengeWaitTime": 0,
          "challengeWaitBefore": 100,
          "challengeMaxTime": 0
        },
        {
          "challengeNumber": 152,
          "challengeCompletions": 0,
          "challengeWaitTime": 0,
          "challengeWaitBefore": 10,
          "challengeMaxTime": 0
        },
        {
          "challengeNumber": 1,
          "challengeCompletions": 0,
          "challengeWaitTime": 0,
          "challengeWaitBefore": 0,
          "challengeMaxTime": 1000000
        },
        {
          "challengeNumber": 2,
          "challengeCompletions": 0,
          "challengeWaitTime": 0,
          "challengeWaitBefore": 10,
          "challengeMaxTime": 1000000
        },
        {
          "challengeNumber": 3,
          "challengeCompletions": 0,
          "challengeWaitTime": 0,
          "challengeWaitBefore": 10,
          "challengeMaxTime": 1000000
        },
        {
          "challengeNumber": 4,
          "challengeCompletions": 0,
          "challengeWaitTime": 0,
          "challengeWaitBefore": 10,
          "challengeMaxTime": 1000000
        },
        {
          "challengeNumber": 5,
          "challengeCompletions": 0,
          "challengeWaitTime": 0,
          "challengeWaitBefore": 10,
          "challengeMaxTime": 1000000
        },
        {
          "challengeNumber": 6,
          "challengeCompletions": 0,
          "challengeWaitTime": 0,
          "challengeWaitBefore": 10,
          "challengeMaxTime": 1000000
        },
        {
          "challengeNumber": 7,
          "challengeCompletions": 0,
          "challengeWaitTime": 0,
          "challengeWaitBefore": 10,
          "challengeMaxTime": 1000000
        },
        {
          "challengeNumber": 8,
          "challengeCompletions": 0,
          "challengeWaitTime": 0,
          "challengeWaitBefore": 10,
          "challengeMaxTime": 1000000
        },
        {
          "challengeNumber": 9,
          "challengeCompletions": 0,
          "challengeWaitTime": 0,
          "challengeWaitBefore": 10,
          "challengeMaxTime": 1000000
        },
        {
          "challengeNumber": 10,
          "challengeCompletions": 0,
          "challengeWaitTime": 0,
          "challengeWaitBefore": 10,
          "challengeMaxTime": 1000000
        },
        {
          "challengeNumber": 102,
          "challengeCompletions": 0,
          "challengeWaitTime": 0,
          "challengeWaitBefore": 120,
          "challengeMaxTime": 0
        },
        {
          "challengeNumber": 402,
          "challengeCompletions": 1,
          "challengeWaitTime": 0,
          "challengeWaitBefore": 0,
          "challengeMaxTime": 10000
        },
        {
          "challengeNumber": 104,
          "challengeCompletions": 0,
          "challengeWaitTime": 0,
          "challengeWaitBefore": 0,
          "challengeMaxTime": 1000000
        },
        {
          "challengeNumber": 304,
          "challengeCompletions": 0,
          "challengeWaitTime": 0,
          "challengeWaitBefore": 0,
          "challengeMaxTime": 1000000
        },
        {
          "challengeNumber": 152,
          "challengeCompletions": 0,
          "challengeWaitTime": 0,
          "challengeWaitBefore": 50,
          "challengeMaxTime": 1000000
        },
        {
          "challengeNumber": 152,
          "challengeCompletions": 0,
          "challengeWaitTime": 0,
          "challengeWaitBefore": 40,
          "challengeMaxTime": 1000000
        },
        {
          "challengeNumber": 152,
          "challengeCompletions": 0,
          "challengeWaitTime": 0,
          "challengeWaitBefore": 30,
          "challengeMaxTime": 1000000
        },
        {
          "challengeNumber": 152,
          "challengeCompletions": 0,
          "challengeWaitTime": 0,
          "challengeWaitBefore": 20,
          "challengeMaxTime": 1000000
        },
        {
          "challengeNumber": 152,
          "challengeCompletions": 0,
          "challengeWaitTime": 0,
          "challengeWaitBefore": 10,
          "challengeMaxTime": 1000000
        }
      ]
    }
  ],
  "aoagPhase": {
    "startPhase": "ascension",
    "endPhase": "ascension",
    "corruptions": {
      "viscosity": 0,
      "drought": 0,
      "deflation": 0,
      "extinction": 0,
      "illiteracy": 0,
      "recession": 0,
      "dilation": 0,
      "hyperchallenge": 0
    },
    "corruptionLoadoutName": "Loadout AOAG Unlocked Phase",
    "strat": [
      {
        "challengeNumber": 103,
        "challengeCompletions": 0,
        "challengeWaitTime": 0,
        "challengeMaxTime": 0
      },
      {
        "challengeNumber": 152,
        "challengeCompletions": 0,
        "challengeWaitTime": 0,
        "challengeWaitBefore": 100,
        "challengeMaxTime": 0
      },
      {
        "challengeNumber": 901,
        "challengeCompletions": 0,
        "challengeWaitTime": 0,
        "challengeWaitBefore": 1,
        "challengeMaxTime": 0
      }
    ],
    "phaseId": "aoag"
  },
  "corruptionLoadouts": [
    {
      "name": "Loadout AOAG Unlocked Phase",
      "loadout": {
        "viscosity": 0,
        "drought": 0,
        "deflation": 0,
        "extinction": 0,
        "illiteracy": 0,
        "recession": 0,
        "dilation": 0,
        "hyperchallenge": 0
      }
    },
    {
      "name": "Post-C15",
      "loadout": {
        "viscosity": 1,
        "drought": 16,
        "deflation": 1,
        "extinction": 16,
        "illiteracy": 1,
        "recession": 16,
        "dilation": 4,
        "hyperchallenge": 7
      }
    },
    {
      "name": "Full",
      "loadout": {
        "viscosity": 16,
        "drought": 16,
        "deflation": 16,
        "extinction": 16,
        "illiteracy": 16,
        "recession": 16,
        "dilation": 16,
        "hyperchallenge": 16
      }
    },
    {
      "name": "post-AoAG",
      "loadout": {
        "viscosity": 10,
        "drought": 16,
        "deflation": 16,
        "extinction": 16,
        "illiteracy": 16,
        "recession": 16,
        "dilation": 16,
        "hyperchallenge": 16
      }
    },
    {
      "name": "ELO",
      "loadout": {
        "viscosity": 16,
        "drought": 0,
        "deflation": 16,
        "extinction": 16,
        "illiteracy": 0,
        "recession": 16,
        "dilation": 0,
        "hyperchallenge": 16
      }
    }
  ]
}